sslcommerz_lib/__init__.py
sslcommerz_lib/sslcommerz.py
sslcommerz_lib-1.0.dist-info/LICENSE
sslcommerz_lib-1.0.dist-info/METADATA
sslcommerz_lib-1.0.dist-info/WHEEL
sslcommerz_lib-1.0.dist-info/top_level.txt
sslcommerz_lib-1.0.dist-info/RECORD
