Metadata-Version: 2.1
Name: sslcommerz-lib
Version: 1.0
Summary: SSLCOMERZ PAYMENT GATEWAY
Home-page: https://github.com/sajanPoddar/sslcommerz-lib-py
Author: SSLCOMMERZ Developers
Author-email: sajan.sslwireless@gmail.com
License: UNKNOWN
Keywords: sslcommerz,payment,1.0
Platform: UNKNOWN
Classifier: Intended Audience :: Developers
Classifier: Natural Language :: English
Classifier: Operating System :: OS Independent
Classifier: Programming Language :: Python
Classifier: Programming Language :: Python :: 2.7
Classifier: Programming Language :: Python :: 3.2
Classifier: Programming Language :: Python :: 3.3
Classifier: Programming Language :: Python :: 3.4
Classifier: Programming Language :: Python :: 3.5
Classifier: Topic :: Software Development :: Libraries :: Python Modules
